gdlparser-0.0.8.dist-info/METADATA
gdlparser-0.0.8.dist-info/WHEEL
gdlparser.cpython-38-x86_64-linux-gnu.so
gdlparser-0.0.8.dist-info/RECORD
