Metadata-Version: 2.1
Name: gdlparser
Version: 0.0.8
Summary: A parser for GDL (game description language)
Author: Gulshan Singh <gulshan@umich.edu>
Author-Email: Gulshan Singh <gulshan@umich.edu>
License: MIT
